jenkins_client.py
jenkinsclient/__init__.py
jenkinsclient/build.py
jenkinsclient/config.py
jenkinsclient/core.py
jenkinsclient/credentials.py
jenkinsclient/executor.py
jenkinsclient/jenkins_server.py
jenkinsclient/job.py
jenkinsclient/node.py
jenkinsclient/plugin.py
jenkinsclient/queue.py
jenkinsclient-2.0.dist-info/LICENSE
jenkinsclient-2.0.dist-info/METADATA
jenkinsclient-2.0.dist-info/WHEEL
jenkinsclient-2.0.dist-info/entry_points.txt
jenkinsclient-2.0.dist-info/top_level.txt
jenkinsclient-2.0.dist-info/RECORD
