Metadata-Version: 2.1
Name: jenkinsclient
Version: 2.0
Summary: A powerful cross-platform Jenkins command line client which supports multiple instances of Jenkins.
Home-page: https://github.com/hummerstudio/jenkinsclient
Author: TangMing
Author-email: hummerstudio@163.com
License: UNKNOWN
Platform: UNKNOWN
Classifier: Programming Language :: Python :: 3
Classifier: License :: OSI Approved :: MIT License
Classifier: Operating System :: OS Independent
Requires-Python: >=3.6
Requires-Dist: fire
Requires-Dist: jenkinsapi
Requires-Dist: python-jenkins
Requires-Dist: PyYAML
